{
	"info": {
		"_postman_id": "8958d1f1-ea9c-4aca-a7cf-dd0b99e07c07",
		"name": "Taxation",
		"schema": "https://schema.getpostman.com/json/collection/v2.1.0/collection.json"
	},
	"item": [
		{
			"name": "GetAll",
			"protocolProfileBehavior": {
				"disableBodyPruning": true
			},
			"request": {
				"method": "GET",
				"header": [],
				"body": {
					"mode": "raw",
					"raw": "{\r\n    \"TaxDescription\": \"Imposto sobre Renda\",\r\n    \"Percentage\": 0.02\r\n}",
					"options": {
						"raw": {
							"language": "json"
						}
					}
				},
				"url": {
					"raw": "https://localhost:5001/taxation",
					"protocol": "https",
					"host": [
						"localhost"
					],
					"port": "5001",
					"path": [
						"taxation"
					]
				}
			},
			"response": []
		},
		{
			"name": "GetById",
			"protocolProfileBehavior": {
				"disableBodyPruning": true
			},
			"request": {
				"method": "GET",
				"header": [],
				"body": {
					"mode": "raw",
					"raw": "{\r\n    \"id\": 4,\r\n    \"taxDescription\": \"IPVAAA\",\r\n    \"percentage\": 0.5,\r\n    \"effectiveDate\": \"2003-01-01T00:00:00\",\r\n    \"expirationDate\": \"\"\r\n}",
					"options": {
						"raw": {
							"language": "json"
						}
					}
				},
				"url": {
					"raw": "https://localhost:5001/taxation/id=1",
					"protocol": "https",
					"host": [
						"localhost"
					],
					"port": "5001",
					"path": [
						"taxation",
						"id=1"
					]
				}
			},
			"response": []
		},
		{
			"name": "Post",
			"request": {
				"method": "POST",
				"header": [],
				"body": {
					"mode": "raw",
					"raw": "{\r\n    \"taxDescription\": \"IPVA\",\r\n    \"percentage\": 0.5,\r\n    \"effectiveDate\": \"2003-01-01T00:00:00\",\r\n    \"expirationDate\": \"\"\r\n}",
					"options": {
						"raw": {
							"language": "json"
						}
					}
				},
				"url": {
					"raw": "https://localhost:5001/taxation",
					"protocol": "https",
					"host": [
						"localhost"
					],
					"port": "5001",
					"path": [
						"taxation"
					]
				}
			},
			"response": []
		},
		{
			"name": "Put",
			"request": {
				"method": "PUT",
				"header": [],
				"body": {
					"mode": "raw",
					"raw": "{\r\n    \"id\": 4,\r\n    \"taxDescription\": \"IPVAAA\",\r\n    \"percentage\": 0.5,\r\n    \"effectiveDate\": \"2003-01-01T00:00:00\",\r\n    \"expirationDate\": \"\"\r\n}",
					"options": {
						"raw": {
							"language": "json"
						}
					}
				},
				"url": {
					"raw": "https://localhost:5001/taxation/id=4",
					"protocol": "https",
					"host": [
						"localhost"
					],
					"port": "5001",
					"path": [
						"taxation",
						"id=4"
					]
				}
			},
			"response": []
		},
		{
			"name": "Delete",
			"request": {
				"method": "DELETE",
				"header": [],
				"body": {
					"mode": "raw",
					"raw": "{\r\n    \"id\": 4,\r\n    \"taxDescription\": \"IPVAAA\",\r\n    \"percentage\": 0.5,\r\n    \"effectiveDate\": \"2003-01-01T00:00:00\",\r\n    \"expirationDate\": \"\"\r\n}",
					"options": {
						"raw": {
							"language": "json"
						}
					}
				},
				"url": {
					"raw": "https://localhost:5001/taxation/id=4",
					"protocol": "https",
					"host": [
						"localhost"
					],
					"port": "5001",
					"path": [
						"taxation",
						"id=4"
					]
				}
			},
			"response": []
		}
	],
	"protocolProfileBehavior": {}
}